qdrant_edge/__init__.py
qdrant_edge/qdrant_edge.pypy311-pp73-x86_64-linux-gnu.so
qdrant_edge_py-0.5.0.dist-info/METADATA
qdrant_edge_py-0.5.0.dist-info/WHEEL
qdrant_edge_py-0.5.0.dist-info/RECORD
