Metadata-Version: 2.4
Name: qdrant-edge-py
Version: 0.5.0
Author: Qdrant Team <info@qdrant.tech>
Author-email: Qdrant Team <info@qdrant.tech>
License: Apache-2.0
